{
  "schema": "rwa.watch.article.v1",
  "generated_at": "2026-03-12T11:23:49Z",
  "type": "daily",
  "date": "2026-03-12",
  "slug": "recap-1b78c156d2",
  "mode": "full",
  "title": "RWA Market Recap — March 12, 2026 | TVL, Capital Flows & Monitoring Signals",
  "urls": {
    "page": "/analysis/recap-1b78c156d2.html",
    "chart_png": "/analysis/charts/recap-1b78c156d2.png"
  },
  "metrics": {
    "protocol_count": 140,
    "total_tvl_usd_today": 23573174324.626385,
    "low_coverage_count": 2,
    "high_apy_flag_count": 0
  },
  "content": {
    "full_html": "<div class='panel'>Generated daily recap stub (V4 safe mode).</div>"
  },
  "social": {
    "x_post_text": "",
    "x_image_path": "/analysis/charts/recap-1b78c156d2.png"
  }
}